LICENSE
README.md
setup.py
vecstore/__init__.py
vecstore/requirements.txt
vecstore/vecstore.py
vecstore.egg-info/PKG-INFO
vecstore.egg-info/SOURCES.txt
vecstore.egg-info/dependency_links.txt
vecstore.egg-info/not-zip-safe
vecstore.egg-info/requires.txt
vecstore.egg-info/top_level.txt