Metadata-Version: 2.4
Name: vecstore
Version: 0.8.0
Summary: Dynamically expandable Vector Store for embeddings, using the HNSW library
Home-page: https://github.com/ptarau/vecstore.git
Author: Paul Tarau
Author-email: ptarau@gmail.com
License: MIT
License-File: LICENSE
Requires-Dist: numpy
Requires-Dist: hnswlib
Dynamic: author
Dynamic: author-email
Dynamic: description
Dynamic: description-content-type
Dynamic: home-page
Dynamic: license
Dynamic: license-file
Dynamic: requires-dist
Dynamic: summary
